mcsrrankedapy/__init__.py
mcsrrankedapy/client.py
mcsrrankedapy/tester.py
mcsrrankedapy/objects/__init__.py
mcsrrankedapy/objects/exceptions.py
mcsrrankedapy/objects/leaderboards.py
mcsrrankedapy/objects/match_info.py
mcsrrankedapy/objects/user_profile.py
mcsrrankedapy/objects/versus_stats.py
mcsrrankedapy-1.0.3.dist-info/licenses/LICENSE
mcsrrankedapy-1.0.3.dist-info/METADATA
mcsrrankedapy-1.0.3.dist-info/WHEEL
mcsrrankedapy-1.0.3.dist-info/top_level.txt
mcsrrankedapy-1.0.3.dist-info/RECORD
