Metadata-Version: 2.4
Name: mcsrrankedapy
Version: 1.0.3
Summary: An API wrapper for the MCSR Ranked API
Author-email: Myer <myer@myer.wtf>
License: MIT License
Requires-Python: >=3.7
License-File: LICENSE
Requires-Dist: aiohttp
Requires-Dist: pydantic
Dynamic: license-file
